{
  "resolvedId": "C:/Users/eden7/Protofolio-Website/Protofolio-Website/node_modules/element-plus/es/components/menu/src/menu-item-group2.mjs",
  "transforms": [
    {
      "name": "vite:load-fallback",
      "result": "import { defineComponent, openBlock, createElementBlock, normalizeClass, createElementVNode, Fragment, createTextVNode, toDisplayString, renderSlot } from 'vue';\nimport '../../../hooks/index.mjs';\nimport { menuItemGroupProps } from './menu-item-group.mjs';\nimport _export_sfc from '../../../_virtual/plugin-vue_export-helper.mjs';\nimport { useNamespace } from '../../../hooks/use-namespace/index.mjs';\n\nconst COMPONENT_NAME = \"ElMenuItemGroup\";\nconst _sfc_main = defineComponent({\n  name: COMPONENT_NAME,\n  props: menuItemGroupProps,\n  setup() {\n    const ns = useNamespace(\"menu-item-group\");\n    return {\n      ns\n    };\n  }\n});\nfunction _sfc_render(_ctx, _cache, $props, $setup, $data, $options) {\n  return openBlock(), createElementBlock(\"li\", {\n    class: normalizeClass(_ctx.ns.b())\n  }, [\n    createElementVNode(\"div\", {\n      class: normalizeClass(_ctx.ns.e(\"title\"))\n    }, [\n      !_ctx.$slots.title ? (openBlock(), createElementBlock(Fragment, { key: 0 }, [\n        createTextVNode(toDisplayString(_ctx.title), 1)\n      ], 64)) : renderSlot(_ctx.$slots, \"title\", { key: 1 })\n    ], 2),\n    createElementVNode(\"ul\", null, [\n      renderSlot(_ctx.$slots, \"default\")\n    ])\n  ], 2);\n}\nvar MenuItemGroup = /* @__PURE__ */ _export_sfc(_sfc_main, [[\"render\", _sfc_render], [\"__file\", \"/home/runner/work/element-plus/element-plus/packages/components/menu/src/menu-item-group.vue\"]]);\n\nexport { MenuItemGroup as default };\n//# sourceMappingURL=menu-item-group2.mjs.map\n",
      "start": 1700494474236,
      "end": 1700494474411,
      "sourcemaps": null
    },
    {
      "name": "nuxt:layer-aliasing",
      "start": 1700494474411,
      "end": 1700494474411,
      "order": "pre"
    },
    {
      "name": "nuxt:layer-aliasing",
      "start": 1700494474411,
      "end": 1700494474411,
      "order": "pre"
    },
    {
      "name": "nuxt:server-devonly:transform",
      "start": 1700494474411,
      "end": 1700494474411,
      "order": "pre"
    },
    {
      "name": "nuxt:server-devonly:transform",
      "start": 1700494474411,
      "end": 1700494474411,
      "order": "pre"
    },
    {
      "name": "nuxt:client-fallback-auto-id",
      "start": 1700494474411,
      "end": 1700494474411,
      "order": "pre"
    },
    {
      "name": "vite:css",
      "start": 1700494474411,
      "end": 1700494474411,
      "order": "normal"
    },
    {
      "name": "vite:esbuild",
      "start": 1700494474411,
      "end": 1700494474411,
      "order": "normal"
    },
    {
      "name": "vite:json",
      "start": 1700494474411,
      "end": 1700494474411,
      "order": "normal"
    },
    {
      "name": "vite:worker",
      "start": 1700494474411,
      "end": 1700494474411,
      "order": "normal"
    },
    {
      "name": "vite:vue",
      "start": 1700494474411,
      "end": 1700494474411,
      "order": "normal"
    },
    {
      "name": "vite:vue-jsx",
      "start": 1700494474411,
      "end": 1700494474411,
      "order": "normal"
    },
    {
      "name": "replace",
      "start": 1700494474411,
      "end": 1700494474411,
      "order": "normal"
    },
    {
      "name": "replace",
      "start": 1700494474411,
      "end": 1700494474411,
      "order": "normal"
    },
    {
      "name": "nuxt:remove-plugin-metadata",
      "start": 1700494474411,
      "end": 1700494474411,
      "order": "normal"
    },
    {
      "name": "nuxt:remove-plugin-metadata",
      "start": 1700494474411,
      "end": 1700494474411,
      "order": "normal"
    },
    {
      "name": "nuxt:components:imports",
      "start": 1700494474411,
      "end": 1700494474412,
      "order": "normal"
    },
    {
      "name": "replace",
      "start": 1700494474412,
      "end": 1700494474412,
      "order": "normal"
    },
    {
      "name": "ssr-styles",
      "start": 1700494474412,
      "end": 1700494474412,
      "order": "normal"
    },
    {
      "name": "vite:define",
      "start": 1700494474412,
      "end": 1700494474412,
      "order": "normal"
    },
    {
      "name": "vite:css-post",
      "start": 1700494474412,
      "end": 1700494474412,
      "order": "normal"
    },
    {
      "name": "vite:build-html",
      "start": 1700494474412,
      "end": 1700494474412,
      "order": "normal"
    },
    {
      "name": "vite:worker-import-meta-url",
      "start": 1700494474412,
      "end": 1700494474412,
      "order": "normal"
    },
    {
      "name": "vite:asset-import-meta-url",
      "start": 1700494474412,
      "end": 1700494474412,
      "order": "normal"
    },
    {
      "name": "commonjs",
      "start": 1700494474412,
      "end": 1700494474412,
      "order": "normal"
    },
    {
      "name": "vite:dynamic-import-vars",
      "start": 1700494474412,
      "end": 1700494474412,
      "order": "normal"
    },
    {
      "name": "vite:import-glob",
      "start": 1700494474412,
      "end": 1700494474412,
      "order": "normal"
    },
    {
      "name": "nuxt:composable-keys",
      "start": 1700494474412,
      "end": 1700494474412,
      "order": "post"
    },
    {
      "name": "nuxt:composable-keys",
      "start": 1700494474412,
      "end": 1700494474412,
      "order": "post"
    },
    {
      "name": "nuxt:imports-transform",
      "start": 1700494474412,
      "end": 1700494474412,
      "order": "post"
    },
    {
      "name": "nuxt:imports-transform",
      "start": 1700494474412,
      "end": 1700494474412,
      "order": "post"
    },
    {
      "name": "unctx:transform",
      "start": 1700494474412,
      "end": 1700494474412,
      "order": "post"
    },
    {
      "name": "unctx:transform",
      "start": 1700494474412,
      "end": 1700494474412,
      "order": "post"
    },
    {
      "name": "nuxt:pages-macros-transform",
      "start": 1700494474412,
      "end": 1700494474412,
      "order": "post"
    },
    {
      "name": "nuxt:pages-macros-transform",
      "start": 1700494474412,
      "end": 1700494474412,
      "order": "post"
    },
    {
      "name": "element-plus:transform",
      "start": 1700494474412,
      "end": 1700494474412,
      "order": "post"
    },
    {
      "name": "nuxt:tree-shake-template",
      "start": 1700494474412,
      "end": 1700494474412,
      "order": "post"
    },
    {
      "name": "nuxt:components-loader",
      "start": 1700494474412,
      "end": 1700494474412,
      "order": "post"
    },
    {
      "name": "nuxt:tree-shake-composables:transform",
      "start": 1700494474412,
      "end": 1700494474412,
      "order": "post"
    },
    {
      "name": "vite:build-import-analysis",
      "start": 1700494474412,
      "end": 1700494474412,
      "order": "normal"
    },
    {
      "name": "vite:reporter",
      "start": 1700494474412,
      "end": 1700494474412,
      "order": "normal"
    }
  ]
}
